celligner/__init__.py
celligner/limma.py
celligner/params.py
celligner-1.1.0.dist-info/LICENSE
celligner-1.1.0.dist-info/METADATA
celligner-1.1.0.dist-info/WHEEL
celligner-1.1.0.dist-info/entry_points.txt
celligner-1.1.0.dist-info/top_level.txt
celligner-1.1.0.dist-info/RECORD
