Metadata-Version: 2.1
Name: celligner
Version: 1.1.0
Summary: A useful module for alligning cell lines to tumors
Home-page: https://github.com/BroadInstitute/celligner
Author: Jeremie Kalfon
Author-email: jkobject@gmail.com
Classifier: Programming Language :: Python :: 3
Classifier: Intended Audience :: Science/Research
Classifier: Topic :: Scientific/Engineering :: Bio-Informatics
Requires-Python: >=3.5
License-File: LICENSE
Requires-Dist: umap-learn (>=0.3)
Requires-Dist: numpy
Requires-Dist: pandas
Requires-Dist: contrastive (>=1.1)
Requires-Dist: Broad-genepy (>=1.1.2)
Requires-Dist: scikit-learn (>=0.24)
Requires-Dist: umap (>=0.1)
Requires-Dist: scanpy (>=1.8)
Requires-Dist: anndata (>=0.7)
Requires-Dist: scipy
Requires-Dist: bokeh (>=2.3)
Requires-Dist: louvain
Requires-Dist: pynndescent
Provides-Extra: test
Requires-Dist: pytest ; extra == 'test'
Requires-Dist: coverage ; extra == 'test'
Requires-Dist: flake8 ; extra == 'test'
Requires-Dist: black ; extra == 'test'
Requires-Dist: isort ; extra == 'test'
Requires-Dist: pytest-cov ; extra == 'test'
Requires-Dist: codecov ; extra == 'test'
Requires-Dist: mypy ; extra == 'test'
Requires-Dist: gitchangelog ; extra == 'test'
Requires-Dist: mkdocs ; extra == 'test'
